sourtimes/__init__.py
sourtimes/exceptions.py
sourtimes/sour.py
sourtimes-0.0.7.dist-info/LICENSE
sourtimes-0.0.7.dist-info/METADATA
sourtimes-0.0.7.dist-info/WHEEL
sourtimes-0.0.7.dist-info/top_level.txt
sourtimes-0.0.7.dist-info/RECORD
