Metadata-Version: 2.1
Name: sourtimes
Version: 0.0.7
Summary: The Python Eksisozluk API Wrapper
Author-email: Kaan Giray Buzluk <kaangiray26@protonmail.com>
License: GNU GENERAL PUBLIC LICENSE
Project-URL: Homepage, https://github.com/kaangiray26/sourtimes
Project-URL: Documentation, https://sourtimes.readthedocs.io/en/latest/
Project-URL: Bug Tracker, https://github.com/kaangiray26/sourtimes/issues
Classifier: Programming Language :: Python :: 3
Classifier: License :: OSI Approved :: GNU General Public License v3 (GPLv3)
Classifier: Operating System :: OS Independent
Requires-Python: >=3.7
License-File: LICENSE
Requires-Dist: requests
Requires-Dist: lxml
